biblestudytools/__init__.py
biblestudytools/__main__.py
biblestudytools/bible/__init__.py
biblestudytools/bible/exceptions.py
biblestudytools/bible/nav.py
biblestudytools/bible/urls.py
biblestudytools/bible/util.py
biblestudytools/nav.py
biblestudytools-1.0.0a0.dist-info/entry_points.txt
biblestudytools-1.0.0a0.dist-info/WHEEL
biblestudytools-1.0.0a0.dist-info/METADATA
biblestudytools-1.0.0a0.dist-info/RECORD
